odoo/addons/fieldservice_timeline/README.rst
odoo/addons/fieldservice_timeline/__init__.py
odoo/addons/fieldservice_timeline/__manifest__.py
odoo/addons/fieldservice_timeline/hooks.py
odoo/addons/fieldservice_timeline/i18n/es.po
odoo/addons/fieldservice_timeline/i18n/es_AR.po
odoo/addons/fieldservice_timeline/i18n/fieldservice_timeline.pot
odoo/addons/fieldservice_timeline/i18n/it.po
odoo/addons/fieldservice_timeline/i18n/pt_BR.po
odoo/addons/fieldservice_timeline/readme/CONFIGURE.md
odoo/addons/fieldservice_timeline/readme/CONTRIBUTORS.md
odoo/addons/fieldservice_timeline/readme/CREDITS.md
odoo/addons/fieldservice_timeline/readme/DESCRIPTION.md
odoo/addons/fieldservice_timeline/readme/ROADMAP.md
odoo/addons/fieldservice_timeline/static/description/icon.png
odoo/addons/fieldservice_timeline/static/description/index.html
odoo/addons/fieldservice_timeline/tests/__init__.py
odoo/addons/fieldservice_timeline/tests/test_fsm_uninstall.py
odoo/addons/fieldservice_timeline/views/fsm_order.xml
odoo/addons/fieldservice_timeline/views/fsm_team.xml
odoo_addon_fieldservice_timeline-17.0.1.0.0.2.dist-info/METADATA
odoo_addon_fieldservice_timeline-17.0.1.0.0.2.dist-info/WHEEL
odoo_addon_fieldservice_timeline-17.0.1.0.0.2.dist-info/top_level.txt
odoo_addon_fieldservice_timeline-17.0.1.0.0.2.dist-info/RECORD
